allcaps/__init__.py
allcaps/build.py
allcaps/cli.py
allcaps/coordinator.py
allcaps/data.py
allcaps/enums.py
allcaps/loader.py
allcaps/resources/headers/beacon.h
allcaps/resources/templates/coffargs.c.j2
allcaps/resources/templates/dllmain.c.j2
allcaps/resources/templates/main.c.j2
allcaps/resources/templates/serviceexemain.c.j2
allcaps/resources/templates/servicehandler.c.j2
allcaps/resources/templates/servicemain.c.j2
allcaps/source.py
allcaps/templating.py
allcaps/utils.py
allcaps-1.0.0.dist-info/LICENSE-3P.txt
allcaps-1.0.0.dist-info/LICENSE.txt
allcaps-1.0.0.dist-info/METADATA
allcaps-1.0.0.dist-info/WHEEL
allcaps-1.0.0.dist-info/entry_points.txt
allcaps-1.0.0.dist-info/RECORD
